{
	"$schema": "https://schema.management.azure.com/schemas/2015-01-01/deploymentParameters.json#",
	"contentVersion": "1.0.0.0",
	"parameters": {
		"factoryName": {
			"value": "appfactory010721"
		},
		"AzureSqlTESTDB_connectionString": {
			"value": ""
		},
		"AzureSqlitbadb_connectionString": {
			"value": ""
		},
		"AzureSqlrccdb_connectionString": {
			"value": ""
		},
		"azurebloklinkservice2_connectionString": {
			"value": ""
		},
		"rcclinkedservice_connectionString": {
			"value": ""
		},
		"DelimitedText1_properties_typeProperties_fileName": {
			"value": "@CONCAT('Incremental-', pipeline().RunId, '.txt')"
		},
		"DelimitedText1_properties_typeProperties_folderPath": {
			"value": "adftutorial/incrementalcopy"
		}
	}
}